maltopic/__init__.py
maltopic/core.py
maltopic/llms/__init__.py
maltopic/llms/openai.py
maltopic/prompts.py
maltopic/stats.py
maltopic/utils.py
maltopic-1.4.0.dist-info/METADATA
maltopic-1.4.0.dist-info/WHEEL
maltopic-1.4.0.dist-info/licenses/LICENSE
maltopic-1.4.0.dist-info/RECORD
