Metadata-Version: 2.4
Name: maltopic
Version: 1.4.0
Summary: A multi-agent LLM topic modeling library.
License: MIT
License-File: LICENSE
Keywords: topic modeling,LLM,multi-agent,survey analysis,data enrichment,topic deduplication,semantic analysis
Author: Yash Sharma
Author-email: yash91sharma@gmail.com
Requires-Python: >=3.12,<4.0
Classifier: License :: OSI Approved :: MIT License
Classifier: Operating System :: OS Independent
Classifier: Programming Language :: Python :: 3
Classifier: Programming Language :: Python :: 3.12
Classifier: Programming Language :: Python :: 3.13
Classifier: Programming Language :: Python :: 3.14
Classifier: Topic :: Scientific/Engineering :: Artificial Intelligence
Requires-Dist: openai (>=1.79.0,<2.0.0)
Requires-Dist: pandas (>=2.2.3,<3.0.0)
Requires-Dist: tiktoken (>=0.9.0,<0.10.0)
Requires-Dist: tqdm (>=4.67.1,<5.0.0)
Project-URL: Homepage, https://github.com/yash91sharma/MALTopic-py
Project-URL: Repository, https://github.com/yash91sharma/MALTopic-py
